build/lib/build/lib/mailflagger/client.py
build/lib/build/lib/mailflagger/cmd.py
build/lib/build/lib/mailflagger/config.py
build/lib/build/lib/mailflagger/imap.py
build/lib/build/lib/mailflagger/server.py
build/lib/build/lib/mailflagger/plugins/manual.py
build/lib/build/lib/mailflagger/plugins/registry.py
build/lib/build/lib/venv/bin/rst2html.py
build/lib/build/lib/venv/bin/rst2html4.py
build/lib/build/lib/venv/bin/rst2html5.py
build/lib/build/lib/venv/bin/rst2latex.py
build/lib/build/lib/venv/bin/rst2man.py
build/lib/build/lib/venv/bin/rst2odt.py
build/lib/build/lib/venv/bin/rst2odt_prepstyles.py
build/lib/build/lib/venv/bin/rst2pseudoxml.py
build/lib/build/lib/venv/bin/rst2s5.py
build/lib/build/lib/venv/bin/rst2xetex.py
build/lib/build/lib/venv/bin/rst2xml.py
build/lib/build/lib/venv/bin/rstpep2html.py
build/lib/mailflagger/client.py
build/lib/mailflagger/cmd.py
build/lib/mailflagger/config.py
build/lib/mailflagger/imap.py
build/lib/mailflagger/server.py
build/lib/mailflagger/plugins/manual.py
build/lib/mailflagger/plugins/registry.py
build/lib/venv/bin/rst2html.py
build/lib/venv/bin/rst2html4.py
build/lib/venv/bin/rst2html5.py
build/lib/venv/bin/rst2latex.py
build/lib/venv/bin/rst2man.py
build/lib/venv/bin/rst2odt.py
build/lib/venv/bin/rst2odt_prepstyles.py
build/lib/venv/bin/rst2pseudoxml.py
build/lib/venv/bin/rst2s5.py
build/lib/venv/bin/rst2xetex.py
build/lib/venv/bin/rst2xml.py
build/lib/venv/bin/rstpep2html.py
mailflagger/client.py
mailflagger/cmd.py
mailflagger/config.py
mailflagger/imap.py
mailflagger/server.py
mailflagger/plugins/manual.py
mailflagger/plugins/registry.py
venv/bin/rst2html.py
venv/bin/rst2html4.py
venv/bin/rst2html5.py
venv/bin/rst2latex.py
venv/bin/rst2man.py
venv/bin/rst2odt.py
venv/bin/rst2odt_prepstyles.py
venv/bin/rst2pseudoxml.py
venv/bin/rst2s5.py
venv/bin/rst2xetex.py
venv/bin/rst2xml.py
venv/bin/rstpep2html.py
mailflagger-0.1.0.dist-info/METADATA
mailflagger-0.1.0.dist-info/WHEEL
mailflagger-0.1.0.dist-info/entry_points.txt
mailflagger-0.1.0.dist-info/top_level.txt
mailflagger-0.1.0.dist-info/RECORD
