Metadata-Version: 2.1
Name: mailflagger
Version: 0.1.0
Summary: A program which flags emails, typically after an incoming payment
Home-page: https://mailflagger.org
Author: Krzysztof Jurewicz
Author-email: krzysztof.jurewicz@gmail.com
License: UNKNOWN
Platform: UNKNOWN
Classifier: Development Status :: 3 - Alpha
Classifier: Environment :: No Input/Output (Daemon)
Classifier: Environment :: MacOS X :: Cocoa
Classifier: Environment :: Win32 (MS Windows)
Classifier: Environment :: X11 Applications :: GTK
Classifier: Framework :: AsyncIO
Classifier: Intended Audience :: End Users/Desktop
Classifier: License :: OSI Approved :: Apache Software License
Classifier: Natural Language :: English
Classifier: Operating System :: MacOS :: MacOS X
Classifier: Operating System :: Microsoft :: Windows
Classifier: Operating System :: POSIX
Classifier: Programming Language :: Python :: 3.8
Classifier: Topic :: Communications :: Email :: Filters
Requires-Python: >=3.8, <4
Requires-Dist: pyzmq (<20,>=19)
Requires-Dist: setuptools
Requires-Dist: msgpack (<2,>=1)
Provides-Extra: gui
Requires-Dist: wxpython (==4.0.7.post2) ; extra == 'gui'
Requires-Dist: Gooey (==1.0.3) ; extra == 'gui'
